nbodysim/__init__.py
nbodysim/exceptions.py
nbodysim/main.py
nbodysim/nbody.py
nbodysim/nmath.py
nbodysim/orbit_plotter.py
nbodysim/three_body.py
nbodysim/integrators/__init__.py
nbodysim/integrators/euler.py
nbodysim/integrators/euler_cromer.py
nbodysim/integrators/integrator.py
nbodysim/integrators/leapfrog_2.py
nbodysim/integrators/leapfrog_3.py
nbodysim/integrators/leapfrog_3_sync.py
nbodysim/integrators/main.py
nbodysim/stability_investigator/__init__.py
nbodysim/stability_investigator/main.py
nbodysim/stability_investigator/mp_stability_plotter.py
nbodysim/stability_investigator/stability_analyser.py
nbodysim/stability_investigator/stability_plotter.py
nbodysim-1.0.3.dist-info/LICENSE
nbodysim-1.0.3.dist-info/METADATA
nbodysim-1.0.3.dist-info/WHEEL
nbodysim-1.0.3.dist-info/top_level.txt
nbodysim-1.0.3.dist-info/RECORD
