Metadata-Version: 2.1
Name: nbodysim
Version: 1.0.3
Summary: N-Body simulator and analyser
Home-page: https://github.com/alv31415/n-body-problem
Author: Antonio León Villares
Author-email: aleonvillares31415@gmail.com
Project-URL: Bug Tracker, https://github.com/pypa/sampleproject/issues
Classifier: Programming Language :: Python :: 3
Classifier: License :: OSI Approved :: MIT License
Classifier: Operating System :: OS Independent
Requires-Python: >=3.6
License-File: LICENSE
